tweetsold/__init__.py
tweetsold-0.2.dist-info/DESCRIPTION.rst
tweetsold-0.2.dist-info/METADATA
tweetsold-0.2.dist-info/RECORD
tweetsold-0.2.dist-info/WHEEL
tweetsold-0.2.dist-info/metadata.json
tweetsold-0.2.dist-info/top_level.txt
