Metadata-Version: 2.0
Name: tweetsold
Version: 0.2
Summary: Search past 7 days tweets.
Home-page: https://github.com/akash0824/tweetsold
Author: Akash kumar
Author-email: akashkumar0824@gmail.com
License: UNKNOWN
Keywords: twitter,tweets,python,past tweets
Platform: UNKNOWN
